sfstart/sfstart.py
sfstart-0.1.0.dist-info/METADATA
sfstart-0.1.0.dist-info/WHEEL
sfstart-0.1.0.dist-info/RECORD
