Metadata-Version: 2.1
Name: sfstart
Version: 0.1.0
Summary: 
Author: songfei
Author-email: 623667783@qq.com
Requires-Python: >=3.11,<4.0
Classifier: Programming Language :: Python :: 3
Classifier: Programming Language :: Python :: 3.11
Requires-Dist: numpy (>=1.24.2,<2.0.0)
